buzzword/__init__.py
buzzword/__main__.py
buzzword/create.py
buzzword/parts/__init__.py
buzzword/parts/configure.py
buzzword/parts/explore.py
buzzword/parts/helpers.py
buzzword/parts/main.py
buzzword/parts/nav.py
buzzword/parts/start.py
buzzword/parts/strings.py
buzzword/parts/style.py
buzzword/parts/tabs.py
buzzword/parts/assets/__init__.py
buzzword/parts/assets/bolt.jpg
buzzword/parts/assets/bolt.png
buzzword/parts/assets/custom.css
buzzword/parts/assets/favicon.ico
buzzword-1.2.3.data/data/buzzword/parts/assets/__init__.py
buzzword-1.2.3.data/data/buzzword/parts/assets/bolt.jpg
buzzword-1.2.3.data/data/buzzword/parts/assets/bolt.png
buzzword-1.2.3.data/data/buzzword/parts/assets/custom.css
buzzword-1.2.3.data/data/buzzword/parts/assets/favicon.ico
buzzword-1.2.3.data/data/docs/about.md
buzzword-1.2.3.data/data/docs/building.md
buzzword-1.2.3.data/data/docs/depgrep.md
buzzword-1.2.3.data/data/docs/guide.md
buzzword-1.2.3.data/data/docs/index.md
buzzword-1.2.3.data/data/docs/requirements.txt
buzzword-1.2.3.data/data/docs/run.md
buzzword-1.2.3.data/scripts/buzzword
buzzword-1.2.3.data/scripts/buzzword-create
docs/about.md
docs/building.md
docs/depgrep.md
docs/guide.md
docs/index.md
docs/requirements.txt
docs/run.md
buzzword-1.2.3.dist-info/LICENSE
buzzword-1.2.3.dist-info/METADATA
buzzword-1.2.3.dist-info/WHEEL
buzzword-1.2.3.dist-info/top_level.txt
buzzword-1.2.3.dist-info/RECORD
