Metadata-Version: 2.1
Name: buzzword
Version: 1.2.3
Summary: Web-app for corpus linguistics
Home-page: UNKNOWN
Author: Danny McDonald
Author-email: daniel.mcdonald@uzh.ch
License: MIT
Platform: UNKNOWN
Requires-Dist: buzz (>=3.0.6)
Requires-Dist: python-dotenv (==0.10.3)
Requires-Dist: flask (==1.1.1)
Requires-Dist: dash (==1.1.1)
Requires-Dist: dash-core-components (==1.1.1)
Requires-Dist: dash-html-components (==1.0.0)
Requires-Dist: dash-renderer (==1.0.0)
Requires-Dist: dash-table (==4.1.0)
Requires-Dist: dash-daq (==0.1.7)
